{
  "isaretler": [
    {
      "text": {
        "sira_no": 45046,
        "parca_adi": "Şânına geldi Kur'an",
        "seslendiren": "A. Özhan",
        "url": "https://www.mediafire.com/download/rre68wrikyys14q/saninageldi.mp3"
      },
      "id": 202508292247,
      "category": "kaynak/aheng"
    },
    {
      "text": {
        "sira_no": 45047,
        "parca_adi": "Nikriz peşrev",
        "seslendiren": "D. Türkan",
        "url": "https://www.mediafire.com/download/5lbvhb5s22l5uh0/nikrizpresrev_dturkan.mp3"
      },
      "id": 202508292247,
      "category": "kaynak/aheng"
    },
    {
      "text": {
        "sira_no": 45048,
        "parca_adi": "Nihavend saz semaisi",
        "seslendiren": "Sazlardan",
        "url": "https://www.mediafire.com/download/za893nj6xdgudou/nihavendsazsemaisi_ens.mp3"
      },
      "id": 202508292247,
      "category": "kaynak/aheng"
    },
    {
      "text": {
        "sira_no": 45049,
        "parca_adi": "Bulan özünü",
        "seslendiren": "V. Dalsaldı",
        "url": "https://www.mediafire.com/download/19q9nq4rd3zkxpb/bulanozunu_dalsaldi.mp3"
      },
      "id": 202508292247,
      "category": "kaynak/aheng"
    },
    {
      "text": {
        "sira_no": 45050,
        "parca_adi": "Görenedir görene",
        "seslendiren": "V. Dalsaldı",
        "url": "https://www.mediafire.com/download/se63uxqbmehzxhj/gorenedirgorene_dalsaldi.mp3"
      },
      "id": 202508292247,
      "category": "kaynak/aheng"
    },
    {
      "text": {
        "sira_no": 45051,
        "parca_adi": "Gülbang, osmanlı davulları",
        "seslendiren": "K. Erguner",
        "url": "https://www.mediafire.com/download/a7dtk3hbs2b6s3v/gulbang_erguner.mp3"
      },
      "id": 202508292247,
      "category": "kaynak/aheng"
    },
    {
      "text": {
        "sira_no": 45052,
        "parca_adi": "İksir-i azam",
        "seslendiren": "A. Özhan",
        "url": "https://www.mediafire.com/download/3vdyg599toqsmbv/iksiriazamdir.mp3"
      },
      "id": 202508292247,
      "category": "kaynak/aheng"
    },
    {
      "text": {
        "sira_no": 45053,
        "parca_adi": "Kazakistan, Tika",
        "seslendiren": "Tika",
        "url": "https://www.mediafire.com/download/9rb39al3aw8h2m4/kazakistan_tika.mp3"
      },
      "id": 202508292247,
      "category": "kaynak/aheng"
    },
    {
      "text": {
        "sira_no": 45054,
        "parca_adi": "Pirlere niyaz ederiz",
        "seslendiren": "E. Bektaş",
        "url": "https://www.mediafire.com/download/7s0fdz54moplpib/pirlereniyazederiz_erkanbektas.mp3"
      },
      "id": 202508292247,
      "category": "kaynak/aheng"
    },
    {
      "text": {
        "sira_no": 45055,
        "parca_adi": "Subhanel ebdiyyil ebed",
        "seslendiren": "H. Necipoğlu",
        "url": "https://www.mediafire.com/download/5d15ejhwvcraaep/zikir_hn.mp3"
      },
      "id": 202508292247,
      "category": "kaynak/aheng"
    },
    {
      "text": {
        "sira_no": 45056,
        "parca_adi": "Zahîd bizi tân eyleme",
        "seslendiren": "M. Yüzyıl",
        "url": "https://www.mediafire.com/download/drrguutl2prbpnb/zahidbizi_my.mp3"
      },
      "id": 202508292247,
      "category": "kaynak/aheng"
    },
    {
      "text": {
        "sira_no": 45057,
        "parca_adi": "Yine aşkın sırrı düştü",
        "seslendiren": "A. Özhan",
        "url": "https://www.mediafire.com/download/eg1v91tga71efva/yineaskinsirr_acem.mp3"
      },
      "id": 202508292247,
      "category": "kaynak/aheng"
    },
    {
      "text": {
        "sira_no": 45058,
        "parca_adi": "Yar yüreğim yar, gör ki neler var",
        "seslendiren": "A. Özhan",
        "url": "https://www.mediafire.com/download/wiveyb56396tocj/yaryuregimyar_sbuselik.mp3"
      },
      "id": 202508292247,
      "category": "kaynak/aheng"
    },
    {
      "text": {
        "sira_no": 45059,
        "parca_adi": "Ya azizi ya Mısri",
        "seslendiren": "U. Sezikli",
        "url": "https://www.mediafire.com/download/ldput5tqo1v0846/yamisri.mp3"
      },
      "id": 202508292246,
      "category": "kaynak/aheng"
    },
    {
      "text": {
        "sira_no": 45060,
        "parca_adi": "Severim ben seni candan içeri",
        "seslendiren": "Yarkın",
        "url": "https://www.mediafire.com/download/j5vnxx6lzmfyzzo/severimbenseni_yarkin.mp3"
      },
      "id": 202508292246,
      "category": "kaynak/aheng"
    },
    {
      "text": {
        "sira_no": 45061,
        "parca_adi": "Nice feryad edip",
        "seslendiren": "A. Özhan",
        "url": "https://www.mediafire.com/download/s1glfkcg1kmvbs4/niceferyadedip_ozhan.mp3"
      },
      "id": 202508292246,
      "category": "kaynak/aheng"
    },
    {
      "text": {
        "sira_no": 45062,
        "parca_adi": "Milki bekadan gelmişim",
        "seslendiren": "A. Özhan",
        "url": "https://www.mediafire.com/download/bkey9576423vpp3/milkibekadan_ozhan.mp3"
      },
      "id": 202508292246,
      "category": "kaynak/aheng"
    },
    {
      "text": {
        "sira_no": 45063,
        "parca_adi": "İstediğimi buldum",
        "seslendiren": "A. Özhan",
        "url": "https://www.mediafire.com/download/31j1yn0zm5t7az9/istedigimibuldum_ozhan.mp3"
      },
      "id": 202508292246,
      "category": "kaynak/aheng"
    },
    {
      "text": {
        "sira_no": 45064,
        "parca_adi": "Allah, Vâhid, Ehâd, Sâmed",
        "seslendiren": "A. Özhan",
        "url": "https://www.mediafire.com/download/jg32a3ndl1ccrj8/hasanrizaefendi_20.mp3"
      },
      "id": 202508292246,
      "category": "kaynak/aheng"
    },
    {
      "text": {
        "sira_no": 45065,
        "parca_adi": "Bir kez gönül yıktın ise",
        "seslendiren": "M. Torun",
        "url": "https://www.mediafire.com/download/kfdmsqhbix6r1xh/birkezgonulyiktinise_mtorun.mp3"
      },
      "id": 202508292246,
      "category": "kaynak/aheng"
    },
    {
      "text": {
        "sira_no": 45066,
        "parca_adi": "Serin Serviler, Saz eseri",
        "seslendiren": "Yansımalar",
        "url": "https://www.mediafire.com/download/8c743k3m3c3ec03/104-serinserviler.mp3"
      },
      "id": 202508292246,
      "category": "kaynak/aheng"
    },
    {
      "text": {
        "sira_no": 450690,
        "parca_adi": "Seyyâh olp yâr yolunda",
        "seslendiren": "M. Kemiksiz",
        "url": "https://www.mediafire.com/file/tieq1j35ar555ae/256-seyyaholup.mp3"
      },
      "id": 202508292246,
      "category": "kaynak/aheng"
    },
    {
      "text": {
        "sira_no": 45067,
        "parca_adi": "Seyyâh olp yâr yolunda",
        "seslendiren": "M. Kemiksiz",
        "url": "https://www.mediafire.com/file/tieq1j35ar555ae/256-seyyaholup.mp3"
      },
      "id": 202508292246,
      "category": "kaynak/aheng"
    },
    {
      "text": {
        "sira_no": 450699,
        "parca_adi": "Seyyâh olp yâr yolunda",
        "seslendiren": "M. Kemiksiz",
        "url": "https://www.mediafire.com/file/tieq1j35ar555ae/256-seyyaholup.mp3"
      },
      "id": 450699,
      "category": "kaynak/aheng"
    },
    {
      "id": 202508290735,
      "category": "sabahnesesi",
      "text": "~\nArzunun olduğu yerde seçim, çatışma ve esâret va..."
    },
    {
      "id": 202508280758,
      "category": "sabahnesesi",
      "text": "~\nÂlemde nefes gibi önce san'at görmedim \n[Ş. Nakş..."
    },
    {
      "id": 202508271706,
      "category": "yoldacevrilenler",
      "text": "[YOLDA ÇEVRİLENLER'DEN]\n\n•\nKemâle dönüşüm celâlle ..."
    }
  ]
}