{
  "isaretler": [
    {
      "text": {
      "sira_no": 1397,
      "parca_adi": "Doğu Vadileri",
      "seslendiren": "B. Tahir",
      "url": "https://www.mediafire.com/file/agnebct9q2h3dba/ahura.mp3"
    },
      "id": 202509291015,
      "category": "kaynak/baska"
    },
    {
      "text": "[SÖYLEŞİ KAYITLARI'DAN]\n\nİyiliği emreden Tanrı, kötülüğe izin vermiştir. \nÇünkü çok daha büyük bir iyilik için evrilir h...",
      "id": 202509272042,
      "category": "soylesikayitlari"
    },
    {
      "text": "[SÖYLEŞİ KAYITLARI'NDAN]\n\n- Var olmanın dayanılmaz ağırlığı bir nefesçik düşse ya sırtımdan...\n\nTadayım dersen bir anda ...",
      "id": 202509271104,
      "category": "soylesikayitlari"
    },
    {
      "text": {
        "sira_no": 1396,
        "parca_adi": "Nikriz bağlı",
        "seslendiren": "A. Aşk",
        "url": "https://www.mediafire.com/file/odiqfg64wiykh4s/nikrizbagli.mp3"
      },
      "id": 202509252021,
      "category": "kaynak/baska"
    },
    {
      "text": "~\nÇok çok çok \nDaha daha daha...\n~\n\nCümle içinde geçen \nHer \"daha\"\nŞimdi olan değil \nBundan başka \nBundan öte \nBundan zi...",
      "id": 202509250924,
      "category": "sabahnesesi"
    },
    {
      "text": "[SÖYLEŞİ KAYITLARI'NDAN]\n\n- Nasılsınız bakalım?\n\n- Hayat mücadelesi \n\nMücadele \nCedel\nMünakaşa \nÇekişme \n\nAma hayattan v...",
      "id": 202509242134,
      "category": "soylesikayitlari"
    },
    {
      "text": "~\n\nA  benim  canım,\nHer nefes \nŞu ikinin birinde dur~aksın:\n\nya boşlukla dolusun \nya da dolulukla boşsun\n\nSabâhu'n-nûr v...",
      "id": 202509240834,
      "category": "sabahnesesi"
    },
    {
      "text": "[SÖYLEŞİ KAYITLARI'NDAN]\n\nVe ceffe'l-kalem...\nKalem olacakları daha ezelden yazdı hem mürekkebi bile kurudu...\n[Hadîs-i ...",
      "id": 202509222213,
      "category": "soylesikayitlari"
    },
    {
      "text": "[SÖYLEŞİ  KAYITLARI'NDAN]\n\n-  \"Ben-im hikâyem\" nerde başlıyor?\nNe ile başlıyor?\n\nRüyâya geçiş ânı gibi o kadar silik ki ...",
      "id": 202509211735,
      "category": "soylesikayitlari"
    },
    {
      "text": "~\n\nAşkın zıddı yoktur.\n\nKorktuğunuz her şey, henüz tanımadığınız bir biçimde aşktır...\n\n\"Aşk olsun\" derken \n'Zâten aşk o...",
      "id": 202509180741,
      "category": "sabahnesesi"
    }
  ]
}
