{
  "isaretler": [
    {
      "id": 1767303062467,
      "title": "Ters~yüz",
      "category": "seyirdefteri",
      "content": {
        "id": 1767303062467,
        "title": "Yeni Taslak",
        "author": "BenOlanBen",
        "publishedDate": "2026-01-01T21:30:53.935Z",
        "created_at": "2026-01-01T21:30:53.935Z",
        "article": {
          "header": {
            "background_image": "https://raw.githubusercontent.com/benolanben/atesiask/main/medya/posts/seyirdefteri/202601012449-1767304181440.mp4",
            "date_value": "",
            "mini_title": "",
            "tags": [
              "tersyüz",
              "yol"
            ],
            "title": "Ters~yüz",
            "subtitle": ""
          },
          "main_article": {
            "quotes": [
              {
                "type": "metin",
                "text": "<p></p><p>Ve ardından \"arayış\" çöker.<br><em>Ki \"arayış\", seni beni \"burada\" olmaktan, burada olandan uzaklaştıran bir illüzyondu zâten...</em></p><p>Yani bize engel olan şey, kelimeler hakikat nefesiyle tersinden okununca, yola dönüştü.</p><p><strong>••<br>••<br>•</strong></p><p> <br></p>"
              }
            ]
          }
        }
      },
      "created_at": "2026-01-01T21:31:02.467Z",
      "updated_at": "2026-01-01T21:49:34.983Z"
    },
    {
      "id": 1767300539196,
      "title": "Boya küpü",
      "category": "seyirdefteri",
      "content": {
        "id": 1767300539196,
        "title": "Yeni Taslak",
        "author": "BenOlanBen",
        "publishedDate": "2026-01-01T20:48:50.271Z",
        "created_at": "2026-01-01T20:48:50.271Z",
        "article": {
          "header": {
            "background_image": "https://raw.githubusercontent.com/benolanben/atesiask/main/medya/posts/seyirdefteri/202601012416-1767302199411.mp4",
            "date_value": "",
            "mini_title": "",
            "tags": [
              "Darusselam",
              "boya",
              "gölge",
              "renk",
              "ışık"
            ],
            "title": "Boya küpü",
            "subtitle": ""
          },
          "main_article": {
            "quotes": [
              {
                "type": "metin",
                "text": "<p>~<br><br>Işığın peşine düşmedim.<br>Yeterince hareketsiz uzandım,<br>Tâ ki o beni bulana dek<br>Ve bulan kaybolana dek<br><br>⚡<br>Olanlar oldu<br>...<br>Yorumlanacak hiçbir şey.<br>Daha olunacak hiçbir şey kalmadı.</p><p>Sadece bir bedenin<br>Zaten doğru olanın içinde istirahati...</p><p></p>"
              },
              {
                "type": "alinti",
                "text": "<p>Ve rengin,<br>Ben kendimi hatırlamadan önce<br>Beni hatırlaması</p>",
                "author": "[Zen Bahçeleri'nden]"
              },
              {
                "type": "metin",
                "text": "<p>~</p>"
              },
              {
                "type": "alinti",
                "text": "<p>Biz <strong><em>Allah</em></strong>'ın boyadığı renge boyandık<br>Allah'tan daha güzel boyası olan kim?</p>",
                "author": "[Bakara:138'den]"
              },
              {
                "type": "metin",
                "text": "<p>~<br></p><p><strong>Rüzgarın peşinden koşma...<br>Bulunduğun yerde dur öylece,<br>O saracaktır kollarını senin etrafına;<br>Kalacaksın kucak kucağa.</strong></p><p><br>Ve böylece, zihnin çölünde, bir serap gerçeğe dönüştü.</p><p><br>Gölge ile ışık, aynı madalyonun yansımasıydı artık.<br>Pes etmek denilen o yumuşak devrimi yaşadım;<br><br>Hayır hayır buna pes etmek denemezdi hem hiç de yumuşak değildi.<br>Zira pes etmek, kazanamayacağım için vazgeçiyorum demekti<br>Teslim olmaksa artık kazanmaya ihtiyacım yok demekti zira hiçbir zaman bir savaş olmamıştı!</p><p><br>Dâru's-selâm, tastamam buraya kurulmuştu</p><p><br>Hiçbir şeyi zorlamadan, tüm kapılar kendi kendine açıldı.</p><p><br>Kendi kuyusuna bakan adam, sonunda kuyunun da ona baktığını fark etti.</p><p><br>İşte o an, her şey ters yüz oldu:</p><p><br>Av, avcıyı içine aldı.<br>Seyirci, sahnedeki tek oyuncu oldu.<br>Ve hepsi büsbütün sahneye dahil oldu</p><p><br>Ben mi?</p><p><br>— Ya da “ben” diye►bildiğim o hayâl~et</p><p><br>Evrenin kendini seyrettiği şeffaf bir mercekten başka bir şey değildim.</p><p><br>Düşüşüm, uçuştu aslında.<br>Düştüğümü sandığım boşluk, kanatlarımdı.</p><p><br>Ve şimdi buradayım:</p><p><br>Varım, yoğum,<br>Her şeyim, hiçbir şeyim.</p><p><br><strong>Işıkla aynı nefesi alıp veren bir toz zerresi...<br>Son söz, ilk sessizlikte kayboldu; yok ötesi</strong><br></p>"
              },
              {
                "type": "alinti",
                "text": "<p>Düşüncelerin seslerini bilen biri, nâdiren söz sesiyle konuşur.<br>İnsanlar birbirlerine sözlerle saygı gösterir, sessizlikle severler.<br></p>",
                "author": "[M. Antić'den]"
              },
              {
                "type": "alinti",
                "text": "<p>Sükûnette hakikatin ışığı kendiliğinden parlar.<br>Zihin sâkinleştiğinde, 'ışk kendi yolunu bulur.<br>Ona doğru yükselmezsiniz; sadece olduğunuz yerde durursunuz<br>Ve zaten burada olanın kendini göstermesine izin verirsiniz.<br></p>",
                "author": "[YÜZ SÖZ'den]"
              },
              {
                "type": "metin",
                "text": "<p><br>~</p>"
              }
            ]
          }
        }
      },
      "created_at": "2026-01-01T20:48:59.196Z",
      "updated_at": "2026-01-01T21:19:02.418Z"
    }
  ]
}