{
  "article": {
    "header": {
      "date_value": "6 Oca 2021 00:29",
      "title": "KADRÎ•CANDAN BİLİNCE",
      "mini_title": "agah olasın",
      "tags": [
        ""
      ],
      "subtitle": "",
      "background_image": "https://raw.githubusercontent.com/benolanben/atesiask/main/medya/kendinolmayageldin/136723833_158172606074404_5509868530251303734_n_18136910782086875.jpg"
    },
    "main_article": {
      "quotes": [
        {
          "type": "baslik",
          "text": "KADRÎ•CANDAN BİLİNCE"
        },
        {
          "type": "metin",
          "text": "[KADRÎ•CANDAN BİLİNCE]\n            Her sonuç, doğrulanmak ister.\n            Her özne, kendini sınar ve kendi biricikliğinin, öteki biricikler karşısında ne anlama\n            geldiğini yoklar.\n\n            Bu sınama, O'nun varoluşunu duyumsayışıdır.\n\n            Evren, insan sûretinde kendini fark ediyor, bilinmeyi seviyor, tanınmak istiyor.\n\n            İşte kader, biraz da bu \"sınama özgürlüğü\" olsa gerek.\n\n            Men 'arefe nefse•hû\n            Feqad 'arefe rabbe•hû\n            O nedir bileyim ki ben (ne) olayım?\n\n            Kadrîmiz olmayaydı\n            Kaderimiz de olmazdı\n\n            Kendinin, kaderinin, insanın, evrenin kadrini, değerini candan bilene selâm olsun..."
        }
      ]
    }
  },
  "id": 202101060029
}