{
  "id": 202512191841,
  "title": "Yeni Taslak",
  "author": "BenOlanBen",
  "publishedDate": "2025-12-19T15:26:17.035Z",
  "created_at": "2025-12-19T15:26:17.035Z",
  "article": {
    "header": {
      "background_image": "https://raw.githubusercontent.com/benolanben/atesiask/main/medya/posts/seyirdefteri/202512191841-1766158869451.jpg",
      "date_value": "",
      "mini_title": "",
      "tags": [
        ""
      ],
      "title": "Hem aslına ulaşmaya...",
      "subtitle": ""
    },
    "main_article": {
      "quotes": [
        {
          "type": "metin",
          "text": "<p class=\"mb-4\"><strong>Ey yolcu,<br></strong>Ayak izlerin yolun kendisidir,<br>Başka bir yol var değildir</p>"
        },
        {
          "type": "alinti",
          "text": "<p class=\"mb-4\"><strong>Ey kendi~ne yolcu,<br></strong>Yol yoktur; yol yürüdükçe oluşur.<br>Öyleyse yol yoktur; yürümek vardır...<br></p>",
          "is_colored": true,
          "author": "[YÜZ SÖZ'den]"
        },
        {
          "type": "metin",
          "text": "<p class=\"mb-4\"><strong>- Sana yoldan yana sual ederler...<br>Varlık dağının her cânibi yol olmamış birinden alma bir haber!</strong></p><p class=\"mb-4\">Maneviyat yolunda temel kural:<br>\"YOL diye bir şey yoktur\"</p><p class=\"mb-4\">İkilikte geçen şu dünya rüyası, rüyada hiç görünmeyen bir şeyle görünür ve dünyada~n o şeye giden bir YOL yoktur.</p><p class=\"mb-4\">Zira ikilik ancak zihin~düşüncelerin rüyasında doğru yolu biliyor oysa ki rüyaya yatan, yerinden oynamış değil...<br><br><strong>( 1977 — 2027 )<br></strong>Mezar taşına bile müdahale eden<br>Zihin, hep iki nokta arasında çizer YOLu:<br>Bulunduğun yer ve varmak istediğin yer.</p><p class=\"mb-4\">Yol boyunca her adımda, her nefeste, sana senden yakın olan var...</p><p class=\"mb-4\"><strong>Zihnin sen~i şaşırtmasına izin verme; aşk bilir yolu...</strong><br><br>~<br>Ve sakın korkma ey yolcu,<br>Akışa direnmek de akışa dahil,<br>Yoldan çıkmak da yola dahil...<br>Değil mi ki?<br>Y~OL içinde OL var<br>~</p>"
        },
        {
          "type": "alinti",
          "text": "<p class=\"mb-4\"><strong>Sonsuz YOL var, sonu aynı olan<br>'İnnâ ileyhi râcîun' böyle de olur inan</strong></p>",
          "author": "[A. Kadrî]"
        },
        {
          "type": "metin",
          "text": "<p class=\"mb-4\">~<br>Kayıp dedin, oyun oldu.<br>Aradın, YOL oldu.<br>Buldun sandın, sevinç oldu<br>Ama bir de dönüp bakınca aynaya<br>Hatırladın mı?<br>OLan<br>'O' oldu...<br>~</p>"
        },
        {
          "type": "alinti",
          "text": "<p class=\"mb-4\">Bizim yolumuzun esâsı,<br>Allah’tan gafil olmamak<br>Ve bir cânı incitmemektir.</p>",
          "author": "[Türbedâr Dedem'den]"
        },
        {
          "type": "metin",
          "text": "<p class=\"mb-4\">Pes bir dem yoldan çekilelim<br>Yol olmuşa kulak verelim:</p>"
        },
        {
          "type": "ses",
          "text": "",
          "url": "https://benolanben.com/dinle/baska&54",
          "cover_image": "https://raw.githubusercontent.com/benolanben/atesiask/main/medya/posts/seyirdefteri/202512191841-1766158871959.jpg"
        },
        {
          "type": "metin",
          "text": "<p class=\"mb-4\"><br><br>~</p>"
        }
      ]
    }
  },
  "updated_at": "2026-01-06T21:02:58.283Z",
  "is_protected": false
}