{
  "article": {
    "header": {
      "date_value": "",
      "title": "",
      "mini_title": "agah olasın",
      "tags": [
        ""
      ],
      "subtitle": "",
      "background_image": "https://raw.githubusercontent.com/benolanben/atesiask/main/medya/kuslar/0032_kus.jpg"
    },
    "main_article": {
      "quotes": [
        {
          "type": "metin",
          "text": "Dertli dilinden meğer neler dimişim neler; aşk ile okuna, yüreğine dokuna:\n\ngir melâmet mülküne mâlik olan ol şâhı gör\nebr olub eflâki tuttu ettiğim eyvahı gör\n\ney gözüm görme cihânın efser - i hakanını\nhırkâ - i abdalının başındaki külahı gör\n\nebrüvan mihrâbını bilmez taşa eyler sücûd\nahsen - i takvime bakmaz vaiz - i gümrâhı gör\n\ngirme bezm - i zâhide görme mürâiler yüzün\ndergâh - ı abdala gir de bezm - i hâsullahı gör\n\nbezm - i aşkı bilmeyüb tâ'n eyleme zâhid bizi\nnokta- i bâ ismini zikreyle sırrullahı gör\n\ndön ziyaret eyleme ibrahim'in bünyâdını\ndertli' nin kalbin ziyaret eyle beytullah'ı gör"
        }
      ]
    }
  },
  "id": 202305010166
}