{
  "article": {
    "header": {
      "date_value": "21 Ağu 2015 00:06",
      "title": "",
      "mini_title": "agah olasın",
      "tags": [
        ""
      ],
      "subtitle": "",
      "background_image": "https://raw.githubusercontent.com/benolanben/atesiask/main/medya/umutrehberi/11849855_1606312336284904_1650038397_n.jpg"
    },
    "main_article": {
      "quotes": [
        {
          "type": "metin",
          "text": "Ben günah itdimse yâ Rab afv ü gufrân sendedir\n            Bir esîm-i mücrimim çün cürm ü isyân bendedir\n            Mağfiret kânı keremsin ey kerîm-i âlîşân\n            Rahmetin deryâsına düşse günâhım kandedir\n            Hayr u şer senden idüğin bilürüm ammâ yine\n            İctinâb etmek gerekdir nehiyden çün bendedir\n            Âşıkânın korkusu Hak’dan cüdâ olduğudur\n            Bir nefes kılma cüdâ gönlüm sana efgendedir\n            Kullarına sen yakınsın dâimâ yâ Rabbenâ\n            Gaflet içre bilmediler dilleri perkendedir\n            Dü-cihândan pâk olan diller nazargâhın senin\n            Zâtını dillerde isbât eyleyen gülşendedir\n            Çün azîmü’ş-şânı bildin hamdü lillâh Tâlibâ\n            Pir Hulûsî nâzenin Uşşâkî’ye dil-bendedir\n\n            Bir kırıntı yeter kereminden...\n            www.atesiask.com"
        }
      ]
    }
  },
  "id": 201508210006
}