{
  "article": {
    "header": {
      "date_value": "29 Kas 2017 12:03",
      "title": "DİL YARASI",
      "mini_title": "agah olasın",
      "tags": [
        ""
      ],
      "subtitle": "",
      "background_image": "https://raw.githubusercontent.com/benolanben/atesiask/main/medya/umutrehberi/24253747_293068621213514_6527380769772404736_n.jpg"
    },
    "main_article": {
      "quotes": [
        {
          "type": "metin",
          "text": "[DİL YARASI]\n\n            Ehl-i zâhir dilinde (azmettim, gayret ettim, niyet ettim, şöyle yaptım böyle yaptım,\n            başardım) kendilerine göre küfr olmasa da ehl-i hakîkat nazarında (Rabbim lütfetti,\n            inâyet buyurdu, bir gayret verdi, şöylece bir niyet ettirdi, ihsân buyurdu, muvaffak\n            buyurdu) tercih edilir.\n\n            Her şeyi Hak verir. Dilediği gibi tasarruf eder. Akıl, ilim, irfan ile Hakka vâsıl olan\n            âkiller, âlimler, âriflerin idrâki arttıkça yükseldikçe; tevâzuu da muvâzî ve mütenâzır\n            olarak artar. Mahviyyet başlar zirâ kendini bilmiştir. Ve bu mazhariyyetlerin Hakka âit\n            olduğunu ve kendinde ancak bir zerresinin -mevcûd değil- mütecellî olduğunu anlamıştır.\n            Bu hâl, mertebe-i hicâbdır. Zira Hakka ulaşmak hicâbla mümkündür\n\n            El-fakru fahrî el-fakru fahrî\n            Demedi mi ol âlemler fahri\n            Fakrini zikret fakrini zikret\n            Mahv u fenâda buldu bu gönlüm\n\n            Allah agâh etsin. Âmîn"
        }
      ]
    }
  },
  "id": 201711291203
}