{
  "article": {
    "header": {
      "date_value": "3 May 2017 16:24",
      "title": "NİYÂZ",
      "mini_title": "agah olasın",
      "tags": [
        ""
      ],
      "subtitle": "",
      "background_image": "https://raw.githubusercontent.com/benolanben/atesiask/main/medya/umutrehberi/18298378_1884419208472147_275381169736908800_n.jpg"
    },
    "main_article": {
      "quotes": [
        {
          "type": "metin",
          "text": "[NİYÂZ]\n\n            Hudâyâ 'izzetün hakkı gönül levhin mücellâ it\n            Görün gül-hâne-i dilden seni senden tesellâ it\n\n            Garîbündür dil-i şeydâ kalupdur çünki LÂ içre\n            Ulaşdur aslına şahum geçir sen LÂ'dan İLLÂ it\n\n            Halâs it hayme-i tenden bu gün dil pîçesin Yâ Rab\n            Götür hâk-i mezelletden anun sen kadrin a'lâ it\n\n            Küşâd it mekteb-i aşkın dirîg itme gedâlardan\n            Okunsun nüsha-i kudret dilim medhine gûyâ it\n\n            Ebâ Bekr ü Ömer Osman Aliyyü'l Murtazâ hakkı\n            Habibim lütf idüp Murâdî'n keremden nazmın imzâ it"
        }
      ]
    }
  },
  "id": 201705031624
}