{
  "article": {
    "header": {
      "date_value": "28 Eyl 2017 00:00",
      "title": "",
      "mini_title": "agah olasın",
      "tags": [
        ""
      ],
      "subtitle": "",
      "background_image": "https://raw.githubusercontent.com/benolanben/atesiask/main/medya/umutrehberi/21984816_357677044666986_5280416369194565632_n.jpg"
    },
    "main_article": {
      "quotes": [
        {
          "type": "metin",
          "text": "Kerbelâyı yâdedip kan ağla kim ağlamayan gözler\n            göremez!\n\n            Bûse-gâhı Mustafâ ﷺ iken o şâhın gerdeni\n            Nîce hançer vurdular bilmem güruh-i eşkiyâ\n\n            Mehmed Ali Hilmi Dede Baba evlâdından, hem Celveti hem Sadi hem Bektaşi olduğu içün\n            \"Şeyh Türlü\" nâm, Kur'ân'ı ezber okuyan; Üsküdarlı Yusuf Fâhir Baba\n            (v. 1966) ruhaniyyetlerine de selâm olsun yâ hû\n\n            Can gözün açtıkta gördüm yâr ü ağyâr kalmadı,\n            Hep hakîkat oldu âlem çarşı pazar kalmadı\n\n            Ben metaı cismi tebdil eyleyince aşk ile\n            Aşk u şevki Murtezâ'dan başka bir var kalmadı\n\n            Kerbelây-ı cismim oldu şöyle sahrâyı belâ,\n            Bir Hüseyn-i Kerbelâ'dan gayri hemvâr kalmadı\n\n            Fahir'a sırr-ı zebiha erdiğim demdenberi,\n            Benliğim mahvoldu gitti dar ü berdar kalmadı\n\n            Her taraf \"inni enallah\" na'rasın tezkâr eder,\n            Çok şükürler bende benden başka dildâr kalmadı"
        }
      ]
    }
  },
  "id": 201709280000
}