{
  "article": {
    "header": {
      "date_value": "21 Ara 2018 00:31",
      "title": "BOŞALTIYORUZ",
      "mini_title": "agah olasın",
      "tags": [
        ""
      ],
      "subtitle": "",
      "background_image": "https://raw.githubusercontent.com/benolanben/atesiask/main/medya/umutrehberi/46661574_265573230787495_8713559282112344970_n.jpg"
    },
    "main_article": {
      "quotes": [
        {
          "type": "metin",
          "text": "[BOŞALTIYORUZ]\n            Allah'ındır ne varsa göklerde ve ne varsa yeryüzünde ve Allah, her şeyi kavramış,\n            içden ve dıştan çepeçevre kuşatmıştır. [Nisa:126]\n\n            Ressamlar, tablolarını tuval üzerine yaparlar; besteciler ise bestelerini sessizlik\n            üzerine. Demek ki sanatın icrâsı için boş bir alan lazım, ben yaptım ben ettim zannından\n            sıyrılıp akışa direnmeden, sürtünme katsayısını sıfıra indirmek lazım ki resmin\n            güzelliği senin tuvalinden de görünsün, bir bitmeyecek zevk versin beste!\n\n            Acziyet, mahviyet, fakr u fenâ giyinip boş olmak lazım cümle kayıtlardan ki ikilik\n            çıkarıp gürültü yapmayalım!\n\n            İyi düşün, bir evi kullanılabilir (hayatı yaşanabilir) kılan, eşyalardan çok, içindeki\n            boşluktur.\n\n            Kendinden boş.olan, benliği boşaltan can, her yerde Hakk'ı görebilir; tıpkı kendini\n            göremediği halde âlemi bir güzel seyreden göz bebeği gibi\n\n            Önce ben diyen cümleleri boşalttığımız, hakîkatiyle dopdolu demler, safâlar olsun"
        }
      ]
    }
  },
  "id": 201812210031
}