{
  "article": {
    "header": {
      "date_value": "9 Nis 2019 10:04",
      "title": "UZ.ATMADAN",
      "mini_title": "agah olasın",
      "tags": [
        ""
      ],
      "subtitle": "",
      "background_image": "https://raw.githubusercontent.com/benolanben/atesiask/main/medya/umutrehberi/54731537_358711041653693_8085323021320101843_n.jpg"
    },
    "main_article": {
      "quotes": [
        {
          "type": "metin",
          "text": "[UZ.ATMADAN]\n            Efendi Hazretleri anlatırdı... Tohum şimdi meyvaya durdu; eh vakti varmış meğer...\n            Gelmiş Mâcir Halil Efendi, Rumeli’den, göçmen, Tire’ye. Gitmişler, tütün kırıyorlar,\n            çapa yapıyorlar. Almış masrafını, Cuma günü, Cuma’yı da kılayım, çardağa öyle gideyim,\n            demiş. Hoca uzatmış işi, cehenneme tıkmış, ateşe atmış, neyse sual sual üstüne... yol\n            yokuş, iş müşkül!\n\n            Laf uzayınca canı sıkılıyor Halil Efendinin; “Hocam, ne kaaa söylersin! O ka somayacak\n            Allah”, Hoca da insaflıymış; “Peki ne soracak?” diyor. “Kulum, ben sendeydim, sen\n            nerdeydin?” “Ben de sendeydim”, “Oop geç bu tarafa”, “Yoktu aberim be ya... bunca\n            zamandır misafirim bilemedim benim, bende olduğunun”, “Oop geç bu tarafa”, “O ka be”...\n            İşte biz bunu öğrenmeye geldik erenlerim"
        }
      ]
    }
  },
  "id": 201904091004
}