{
  "article": {
    "header": {
      "date_value": "7 Ağu 2019 23:15",
      "title": "KENDİNDE•N",
      "mini_title": "agah olasın",
      "tags": [
        ""
      ],
      "subtitle": "",
      "background_image": "https://raw.githubusercontent.com/benolanben/atesiask/main/medya/umutrehberi/66410696_216285942674330_8128908955309974853_n.jpg"
    },
    "main_article": {
      "quotes": [
        {
          "type": "metin",
          "text": "[KENDİNDE•N]\n            Sabahtan kalktım da eyledim nazar\n            Hazret-i Yûsuf'a kurulmuş pazar\n            Karşıda Züleyhâ zülfünü tarar\n            Kendinden kendine görünmek için\n\n            Güneş kıvılcımı, yapmıştır süsü\n            Nûr-u ilâhîden onun örtüsü\n            Bu canın bahâsı, onun görgüsü\n            Kendinden kendine görünmek için\n\n            Her tarafı sarmış O'nun boyası\n            Âşıklar seyreder O'nu doyası\n            Bu felekten geniş eli ayası\n            Kendinden kendine görünmek için\n\n            Gözleri geniştir Arş-ı âlâ'dan\n            Her vakit seyreder o Yâr, bâlâdan\n            Bütün âşıkları O'dur ağlatan\n            Kendinden kendine görünmek için\n\n            Adem ü Havvâ'dan etti tecellî\n            Şark ile garbı da tutuyor eli\n            Dâimâ diridir, yoktur eceli\n            Kendinden kendine görünmek için\n\n            Her vakit diridir, alan gıdâyı,\n            Bütün zerrâtlardan eder edâyı\n            Kendisi insandır, saklar Hudâ'yı,\n            Kendinden kendine görünmek için\n\n            Seyreden unutur mülk ile malı,\n            Aklından çıkarır bütün hayâlı,\n            Görünüyor Vâhid, binbir boyalı,\n            Kendinden kendine görünmek için\n\n            Ne hikmettir, O'nu durmaz ararlar\n            Kendisini koyup taştan sorarlar\n            Eğer görünürse, tuzak kurarlar\n            Kendinden kendine görünmek için\n\n            İhâtâ eylemiş bütün sıfâtı\n            Âşık, okur, yazar, O'ndan âyâtı\n            Nefahtü dilinden alır hayâtı\n            Kendinden kendine görünmek için\n\n            Onlar görür görmez, candan geçerler,\n            Görünmez, bilinmez ele göçerler,\n            Dirilik suyunu ordan içerler\n            Kendinden kendine görünmek için\n\n            Durmadan övdüğüm, \"Âdem gönlüdür\"\n            Ordan Hudâ söyler, kendi ölüdür\n            Solup da çürümez, \"diri gülü\" dür\n            Kendinden kendine görünmek için\n\n            Âşığın gözleri, O Gül'e bakar\n            O Gül, durmaz açar, dâimâ kokar\n            Bu ne hikmet yâ Rab, görenler korkar\n            Kendinden kendine görünmek için\n\n            Bir.gülü tanıyanın gözleri, yüzü bin.güle de dönse hep o gülü görür. O gül ki her dem\n            tâzedir, her nefes yeniden açar, her açışında nice başka türlü koku saçar. Yâni yeni\n            sözler söyler, bu sözlerle yeni yeni tomurcuklar yetiştirir. Hakikatin kokusunu almayı\n            dileyen herkes dirilmeye başladı demektir\n\n            Ne hikmetse bu vahdet neş'esini kavramayan zevksizler, muhabbetten nasipsizler, ona\n            bakarlar da \"bizi dînimizden edecek\" diye ondan korkar olurlar yâ hû..."
        }
      ]
    }
  },
  "id": 201908072315
}