{
  "article": {
    "header": {
      "date_value": "24 Haz 2019 05:59",
      "title": "LAST WORDS",
      "mini_title": "agah olasın",
      "tags": [
        ""
      ],
      "subtitle": "",
      "background_image": "https://raw.githubusercontent.com/benolanben/atesiask/main/medya/umutrehberi/65210154_327659658127421_2253131408395065431_n.jpg"
    },
    "main_article": {
      "quotes": [
        {
          "type": "metin",
          "text": "[LAST WORDS]\n            Kendimden kaçmaya çalıştıysam da\n            başaramadım\n            ama hiçbir pişmanlığım falan yok\n            ne de başka bir planım\n            ...\n            Hiç olduğum hem de\n            Hem de bir süreliğine insan olarak\n            Göründüğüm için\n            ...\n            Ben insanlığı denedim\n            Şimdi siz hiçliği deniyorsunuz\n            Sanki son moda bir egzersiz gibi\n            hergün onu kucaklıyorsunuz!\n\n            If I have tried to run away from myself, I have failed. But I have no regrets whatsoever\n            and no further plan for I have been both Nothing, and for a while, a Man. I tried\n            manhood, now you try nothingness, embrace it daily like a trendy new fitness.\n            [IN PRAISE OF NOTHING:2019]"
        }
      ]
    }
  },
  "id": 201906240559
}