{
  "article": {
    "header": {
      "date_value": "7 Haz 2020 03:21",
      "title": "ÇERÇEVE•SİZ",
      "mini_title": "agah olasın",
      "tags": [
        ""
      ],
      "subtitle": "",
      "background_image": "https://raw.githubusercontent.com/benolanben/atesiask/main/medya/umutrehberi/0001_kus.jpg"
    },
    "main_article": {
      "quotes": [
        {
          "type": "metin",
          "text": "[ÇERÇEVE•SİZ]\n            Âlemin esprisi bu; sonsuz sınırsız bir zenginliği, beşer kabuğunun içinde tecrübe\n            ediyor!\n\n            Heyhât bir•noktadan âlem sığıyor: âlemsin sen!\n\n            Güneşi öven, gözünü över: Şâhîd ol ben kör değilim der! Güneş de ona \"Gözün\n            aydın\" der!\n\n            İnsan, sudaki buz zerresi misâli kendi özünün oluşturduğu sonsuz sınırsız okyanusta\n            yüzüp durmaktadır.\n\n            Su/buz, iç/dış arasındaki çeper bir ömür biriktiği kimlik kabuğudur.\n\n            Meğer beni bütünden ayıran o çerçeve yâni oyundaki perde, insanın bâtın ve zâhirine\n            sınır olan etten duvar, tenden kabuk, kıldan duvak sanal benlik kimliğim imiş ve ancak\n            ölünce yâhut u.yanınca gösterirmiş vahdet elin, kalktıkça kesret perdesi\n\n            Sûre-i İhlâs ile kendi kendini târif eden O varken, ek-o ile ek O kurgulayan ego\n            zindanından kurtulmaktır en büyük farz!\n\n            Ne var ki içinde ben olan her söz manâya, her görüntü noktaya, her kap suya bir son ve\n            sınır çiziyor.\n\n            Sessiz sedâsız, görüntüye aldanmadan, siyah bir noktadan, siyah nûr deryâsına karış•ana,\n            hiç ayrılığı olmayana, çerçeve.siz selâm olsun"
        }
      ]
    }
  },
  "id": 202006070321
}