{
  "article": {
    "header": {
      "date_value": "24 Mar 2020 08:43",
      "title": "AKIŞKANDA AKIŞ.TAM",
      "mini_title": "agah olasın",
      "tags": [
        ""
      ],
      "subtitle": "",
      "background_image": "https://raw.githubusercontent.com/benolanben/atesiask/main/medya/umutrehberi/90354725_769988513528352_3205320979081328732_n.jpg"
    },
    "main_article": {
      "quotes": [
        {
          "type": "metin",
          "text": "[AKIŞKANDA AKIŞ.TAM]\n            Ki O’dur Subhân! KULUNU cehâletin karanlığından hakîkatlerin aydınlığına sevk eden...\n            [İsrâ:1 Meâli]\n\n            Sâhibiyle aynı frekansta titreşen, O'nun nâmına seve seve iş gördüğünden kendisine\n            özgürlük verilen insana KUL, öz(ü)gürlüğü ego ile kısıtlanmış, zorla iş görene KÖLE\n            denir.\n\n            Tanrı insanda ne kadar mevcut ise insan o kadar özgürdür, demek oluyor ki insan ne kadar\n            aşkla bezenmiş ise o kadar özgürce iş görür.\n\n            Özünün akışını kabûl et, sistemin sâhibinin senden de işlemesine izin ver, yalıtkan\n            olduğundan akışa mâni benliğini aradan çek, sâdece sessiz bir tanık ol, bütünün akışını\n            hisset, aç gözünü âlem aynasında birlik yayını seyret, tekrârı yok bunun."
        }
      ]
    }
  },
  "id": 202003240843
}